[
  {
    "id": 0,
    "row": 104.25,
    "col": 84.25,
    "type": "junction",
    "degree": 4
  },
  {
    "id": 1,
    "row": 218.66666666666666,
    "col": 238.33333333333334,
    "type": "junction",
    "degree": 3
  },
  {
    "id": 2,
    "row": 274.0,
    "col": 323.0,
    "type": "junction",
    "degree": 3
  },
  {
    "id": 3,
    "row": 306.0,
    "col": 394.75,
    "type": "junction",
    "degree": 3
  },
  {
    "id": 4,
    "row": 328.0,
    "col": 412.0,
    "type": "junction",
    "degree": 3
  },
  {
    "id": 6,
    "row": 0.0,
    "col": 171.0,
    "type": "endpoint",
    "degree": 1
  },
  {
    "id": 7,
    "row": 20.0,
    "col": 0.0,
    "type": "endpoint",
    "degree": 1
  },
  {
    "id": 8,
    "row": 142.0,
    "col": 511.0,
    "type": "endpoint",
    "degree": 1
  },
  {
    "id": 9,
    "row": 177.0,
    "col": 28.0,
    "type": "endpoint",
    "degree": 1
  },
  {
    "id": 10,
    "row": 398.0,
    "col": 511.0,
    "type": "endpoint",
    "degree": 1
  },
  {
    "id": 11,
    "row": 469.0,
    "col": 0.0,
    "type": "endpoint",
    "degree": 1
  },
  {
    "id": 12,
    "row": 496.0,
    "col": 170.0,
    "type": "endpoint",
    "degree": 1
  },
  {
    "id": 14,
    "row": 510.0,
    "col": 280.0,
    "type": "endpoint",
    "degree": 1
  }
]