[
  {
    "u": 1,
    "v": 3,
    "key": 0,
    "length": 9.242640687119284,
    "healed": false,
    "geometry": [
      [
        10.0,
        206.0
      ],
      [
        10.0,
        205.0
      ],
      [
        10.0,
        204.0
      ],
      [
        11.0,
        203.0
      ],
      [
        11.0,
        202.0
      ],
      [
        11.0,
        201.0
      ],
      [
        12.0,
        200.0
      ],
      [
        12.0,
        199.0
      ],
      [
        11.0,
        198.0
      ]
    ]
  },
  {
    "u": 1,
    "v": 17,
    "key": 0,
    "length": 56.72792206135785,
    "healed": false,
    "geometry": [
      [
        10.0,
        208.0
      ],
      [
        10.0,
        209.0
      ],
      [
        10.0,
        210.0
      ],
      [
        10.0,
        211.0
      ],
      [
        10.0,
        212.0
      ],
      [
        10.0,
        213.0
      ],
      [
        10.0,
        214.0
      ],
      [
        11.0,
        215.0
      ],
      [
        11.0,
        216.0
      ],
      [
        11.0,
        217.0
      ],
      [
        12.0,
        218.0
      ],
      [
        12.0,
        219.0
      ],
      [
        13.0,
        220.0
      ],
      [
        14.0,
        221.0
      ],
      [
        15.0,
        222.0
      ],
      [
        15.0,
        223.0
      ],
      [
        16.0,
        224.0
      ],
      [
        17.0,
        225.0
      ],
      [
        18.0,
        225.0
      ],
      [
        19.0,
        225.0
      ],
      [
        20.0,
        225.0
      ],
      [
        21.0,
        225.0
      ],
      [
        22.0,
        225.0
      ],
      [
        23.0,
        225.0
      ],
      [
        24.0,
        225.0
      ],
      [
        25.0,
        225.0
      ],
      [
        26.0,
        225.0
      ],
      [
        27.0,
        225.0
      ],
      [
        28.0,
        225.0
      ],
      [
        29.0,
        225.0
      ],
      [
        30.0,
        225.0
      ],
      [
        31.0,
        225.0
      ],
      [
        32.0,
        225.0
      ],
      [
        33.0,
        225.0
      ],
      [
        34.0,
        225.0
      ],
      [
        35.0,
        225.0
      ],
      [
        36.0,
        225.0
      ],
      [
        37.0,
        225.0
      ],
      [
        38.0,
        225.0
      ],
      [
        39.0,
        226.0
      ],
      [
        40.0,
        226.0
      ],
      [
        41.0,
        226.0
      ],
      [
        42.0,
        226.0
      ],
      [
        43.0,
        226.0
      ],
      [
        44.0,
        226.0
      ],
      [
        45.0,
        226.0
      ],
      [
        46.0,
        226.0
      ],
      [
        47.0,
        226.0
      ],
      [
        48.0,
        226.0
      ],
      [
        49.0,
        226.0
      ],
      [
        50.0,
        226.0
      ],
      [
        51.0,
        226.0
      ],
      [
        52.0,
        226.0
      ],
      [
        53.0,
        227.0
      ]
    ]
  },
  {
    "u": 2,
    "v": 4,
    "key": 1,
    "length": 8.414213562373096,
    "healed": false,
    "geometry": [
      [
        12.0,
        172.0
      ],
      [
        12.0,
        173.0
      ],
      [
        13.0,
        174.0
      ],
      [
        13.0,
        175.0
      ],
      [
        13.0,
        176.0
      ],
      [
        13.0,
        177.0
      ],
      [
        13.0,
        178.0
      ],
      [
        13.0,
        179.0
      ],
      [
        13.0,
        180.0
      ]
    ]
  },
  {
    "u": 2,
    "v": 5,
    "key": 0,
    "length": 3.82842712474619,
    "healed": false,
    "geometry": [
      [
        12.0,
        171.0
      ],
      [
        13.0,
        170.0
      ],
      [
        14.0,
        170.0
      ],
      [
        15.0,
        169.0
      ]
    ]
  },
  {
    "u": 3,
    "v": 4,
    "key": 0,
    "length": 16.65685424949238,
    "healed": false,
    "geometry": [
      [
        11.0,
        197.0
      ],
      [
        12.0,
        196.0
      ],
      [
        12.0,
        195.0
      ],
      [
        13.0,
        194.0
      ],
      [
        13.0,
        193.0
      ],
      [
        13.0,
        192.0
      ],
      [
        14.0,
        191.0
      ],
      [
        14.0,
        190.0
      ],
      [
        14.0,
        189.0
      ],
      [
        14.0,
        188.0
      ],
      [
        14.0,
        187.0
      ],
      [
        13.0,
        186.0
      ],
      [
        13.0,
        185.0
      ],
      [
        13.0,
        184.0
      ],
      [
        13.0,
        183.0
      ],
      [
        13.0,
        182.0
      ]
    ]
  },
  {
    "u": 5,
    "v": 6,
    "key": 0,
    "length": 157.48528137423858,
    "healed": false,
    "geometry": [
      [
        15.0,
        168.0
      ],
      [
        15.0,
        167.0
      ],
      [
        15.0,
        166.0
      ],
      [
        15.0,
        165.0
      ],
      [
        15.0,
        164.0
      ],
      [
        15.0,
        163.0
      ],
      [
        15.0,
        162.0
      ],
      [
        15.0,
        161.0
      ],
      [
        15.0,
        160.0
      ],
      [
        15.0,
        159.0
      ],
      [
        15.0,
        158.0
      ],
      [
        15.0,
        157.0
      ],
      [
        15.0,
        156.0
      ],
      [
        15.0,
        155.0
      ],
      [
        15.0,
        154.0
      ],
      [
        15.0,
        153.0
      ],
      [
        15.0,
        152.0
      ],
      [
        15.0,
        151.0
      ],
      [
        15.0,
        150.0
      ],
      [
        15.0,
        149.0
      ],
      [
        15.0,
        148.0
      ],
      [
        16.0,
        147.0
      ],
      [
        16.0,
        146.0
      ],
      [
        16.0,
        145.0
      ],
      [
        16.0,
        144.0
      ],
      [
        16.0,
        143.0
      ],
      [
        16.0,
        142.0
      ],
      [
        16.0,
        141.0
      ],
      [
        16.0,
        140.0
      ],
      [
        16.0,
        139.0
      ],
      [
        16.0,
        138.0
      ],
      [
        16.0,
        137.0
      ],
      [
        16.0,
        136.0
      ],
      [
        16.0,
        135.0
      ],
      [
        16.0,
        134.0
      ],
      [
        16.0,
        133.0
      ],
      [
        16.0,
        132.0
      ],
      [
        16.0,
        131.0
      ],
      [
        16.0,
        130.0
      ],
      [
        16.0,
        129.0
      ],
      [
        16.0,
        128.0
      ],
      [
        16.0,
        127.0
      ],
      [
        16.0,
        126.0
      ],
      [
        16.0,
        125.0
      ],
      [
        16.0,
        124.0
      ],
      [
        16.0,
        123.0
      ],
      [
        16.0,
        122.0
      ],
      [
        16.0,
        121.0
      ],
      [
        16.0,
        120.0
      ],
      [
        16.0,
        119.0
      ],
      [
        16.0,
        118.0
      ],
      [
        16.0,
        117.0
      ],
      [
        16.0,
        116.0
      ],
      [
        16.0,
        115.0
      ],
      [
        16.0,
        114.0
      ],
      [
        16.0,
        113.0
      ],
      [
        16.0,
        112.0
      ],
      [
        16.0,
        111.0
      ],
      [
        16.0,
        110.0
      ],
      [
        16.0,
        109.0
      ],
      [
        16.0,
        108.0
      ],
      [
        15.0,
        107.0
      ],
      [
        15.0,
        106.0
      ],
      [
        15.0,
        105.0
      ],
      [
        15.0,
        104.0
      ],
      [
        15.0,
        103.0
      ],
      [
        15.0,
        102.0
      ],
      [
        15.0,
        101.0
      ],
      [
        15.0,
        100.0
      ],
      [
        15.0,
        99.0
      ],
      [
        15.0,
        98.0
      ],
      [
        15.0,
        97.0
      ],
      [
        15.0,
        96.0
      ],
      [
        15.0,
        95.0
      ],
      [
        15.0,
        94.0
      ],
      [
        15.0,
        93.0
      ],
      [
        15.0,
        92.0
      ],
      [
        15.0,
        91.0
      ],
      [
        15.0,
        90.0
      ],
      [
        14.0,
        89.0
      ],
      [
        14.0,
        88.0
      ],
      [
        14.0,
        87.0
      ],
      [
        14.0,
        86.0
      ],
      [
        14.0,
        85.0
      ],
      [
        14.0,
        84.0
      ],
      [
        14.0,
        83.0
      ],
      [
        14.0,
        82.0
      ],
      [
        14.0,
        81.0
      ],
      [
        14.0,
        80.0
      ],
      [
        14.0,
        79.0
      ],
      [
        14.0,
        78.0
      ],
      [
        14.0,
        77.0
      ],
      [
        14.0,
        76.0
      ],
      [
        14.0,
        75.0
      ],
      [
        14.0,
        74.0
      ],
      [
        14.0,
        73.0
      ],
      [
        14.0,
        72.0
      ],
      [
        14.0,
        71.0
      ],
      [
        14.0,
        70.0
      ],
      [
        14.0,
        69.0
      ],
      [
        15.0,
        68.0
      ],
      [
        15.0,
        67.0
      ],
      [
        15.0,
        66.0
      ],
      [
        15.0,
        65.0
      ],
      [
        15.0,
        64.0
      ],
      [
        15.0,
        63.0
      ],
      [
        15.0,
        62.0
      ],
      [
        15.0,
        61.0
      ],
      [
        15.0,
        60.0
      ],
      [
        15.0,
        59.0
      ],
      [
        15.0,
        58.0
      ],
      [
        15.0,
        57.0
      ],
      [
        15.0,
        56.0
      ],
      [
        15.0,
        55.0
      ],
      [
        15.0,
        54.0
      ],
      [
        15.0,
        53.0
      ],
      [
        15.0,
        52.0
      ],
      [
        15.0,
        51.0
      ],
      [
        15.0,
        50.0
      ],
      [
        15.0,
        49.0
      ],
      [
        15.0,
        48.0
      ],
      [
        15.0,
        47.0
      ],
      [
        15.0,
        46.0
      ],
      [
        15.0,
        45.0
      ],
      [
        15.0,
        44.0
      ],
      [
        15.0,
        43.0
      ],
      [
        15.0,
        42.0
      ],
      [
        15.0,
        41.0
      ],
      [
        15.0,
        40.0
      ],
      [
        15.0,
        39.0
      ],
      [
        15.0,
        38.0
      ],
      [
        15.0,
        37.0
      ],
      [
        15.0,
        36.0
      ],
      [
        16.0,
        35.0
      ],
      [
        16.0,
        34.0
      ],
      [
        16.0,
        33.0
      ],
      [
        16.0,
        32.0
      ],
      [
        16.0,
        31.0
      ],
      [
        16.0,
        30.0
      ],
      [
        16.0,
        29.0
      ],
      [
        16.0,
        28.0
      ],
      [
        16.0,
        27.0
      ],
      [
        16.0,
        26.0
      ],
      [
        16.0,
        25.0
      ],
      [
        16.0,
        24.0
      ],
      [
        16.0,
        23.0
      ],
      [
        16.0,
        22.0
      ],
      [
        16.0,
        21.0
      ],
      [
        16.0,
        20.0
      ],
      [
        16.0,
        19.0
      ],
      [
        16.0,
        18.0
      ],
      [
        16.0,
        17.0
      ],
      [
        16.0,
        16.0
      ],
      [
        17.0,
        15.0
      ],
      [
        17.0,
        14.0
      ],
      [
        17.0,
        13.0
      ]
    ]
  },
  {
    "u": 5,
    "v": 8,
    "key": 0,
    "length": 94.24264068711928,
    "healed": false,
    "geometry": [
      [
        16.0,
        169.0
      ],
      [
        17.0,
        169.0
      ],
      [
        18.0,
        169.0
      ],
      [
        19.0,
        169.0
      ],
      [
        20.0,
        169.0
      ],
      [
        21.0,
        169.0
      ],
      [
        22.0,
        169.0
      ],
      [
        23.0,
        169.0
      ],
      [
        24.0,
        169.0
      ],
      [
        25.0,
        169.0
      ],
      [
        26.0,
        169.0
      ],
      [
        27.0,
        169.0
      ],
      [
        28.0,
        169.0
      ],
      [
        29.0,
        169.0
      ],
      [
        30.0,
        169.0
      ],
      [
        31.0,
        169.0
      ],
      [
        32.0,
        169.0
      ],
      [
        33.0,
        169.0
      ],
      [
        34.0,
        169.0
      ],
      [
        35.0,
        169.0
      ],
      [
        36.0,
        169.0
      ],
      [
        37.0,
        169.0
      ],
      [
        38.0,
        169.0
      ],
      [
        39.0,
        169.0
      ],
      [
        40.0,
        169.0
      ],
      [
        41.0,
        169.0
      ],
      [
        42.0,
        169.0
      ],
      [
        43.0,
        169.0
      ],
      [
        44.0,
        169.0
      ],
      [
        45.0,
        169.0
      ],
      [
        46.0,
        169.0
      ],
      [
        47.0,
        169.0
      ],
      [
        48.0,
        169.0
      ],
      [
        49.0,
        169.0
      ],
      [
        50.0,
        169.0
      ],
      [
        51.0,
        169.0
      ],
      [
        52.0,
        169.0
      ],
      [
        53.0,
        169.0
      ],
      [
        54.0,
        169.0
      ],
      [
        55.0,
        169.0
      ],
      [
        56.0,
        169.0
      ],
      [
        57.0,
        169.0
      ],
      [
        58.0,
        169.0
      ],
      [
        59.0,
        169.0
      ],
      [
        60.0,
        169.0
      ],
      [
        61.0,
        169.0
      ],
      [
        62.0,
        169.0
      ],
      [
        63.0,
        169.0
      ],
      [
        64.0,
        169.0
      ],
      [
        65.0,
        169.0
      ],
      [
        66.0,
        170.0
      ],
      [
        67.0,
        170.0
      ],
      [
        68.0,
        170.0
      ],
      [
        69.0,
        170.0
      ],
      [
        70.0,
        170.0
      ],
      [
        71.0,
        170.0
      ],
      [
        72.0,
        170.0
      ],
      [
        73.0,
        170.0
      ],
      [
        74.0,
        170.0
      ],
      [
        75.0,
        170.0
      ],
      [
        76.0,
        170.0
      ],
      [
        77.0,
        170.0
      ],
      [
        78.0,
        170.0
      ],
      [
        79.0,
        170.0
      ],
      [
        80.0,
        170.0
      ],
      [
        81.0,
        170.0
      ],
      [
        82.0,
        170.0
      ],
      [
        83.0,
        170.0
      ],
      [
        84.0,
        170.0
      ],
      [
        85.0,
        170.0
      ],
      [
        86.0,
        170.0
      ],
      [
        87.0,
        170.0
      ],
      [
        88.0,
        170.0
      ],
      [
        89.0,
        170.0
      ],
      [
        90.0,
        170.0
      ],
      [
        91.0,
        170.0
      ],
      [
        92.0,
        170.0
      ],
      [
        93.0,
        170.0
      ],
      [
        94.0,
        170.0
      ],
      [
        95.0,
        170.0
      ],
      [
        96.0,
        170.0
      ],
      [
        97.0,
        170.0
      ],
      [
        98.0,
        170.0
      ],
      [
        99.0,
        170.0
      ],
      [
        100.0,
        170.0
      ],
      [
        101.0,
        170.0
      ],
      [
        102.0,
        170.0
      ],
      [
        103.0,
        171.0
      ],
      [
        104.0,
        171.0
      ],
      [
        105.0,
        171.0
      ],
      [
        106.0,
        171.0
      ],
      [
        107.0,
        171.0
      ],
      [
        108.0,
        170.0
      ],
      [
        109.0,
        170.0
      ]
    ]
  },
  {
    "u": 6,
    "v": 16,
    "key": 0,
    "length": 10.82842712474619,
    "healed": false,
    "geometry": [
      [
        17.0,
        11.0
      ],
      [
        16.0,
        10.0
      ],
      [
        16.0,
        9.0
      ],
      [
        16.0,
        8.0
      ],
      [
        15.0,
        7.0
      ],
      [
        15.0,
        6.0
      ],
      [
        15.0,
        5.0
      ],
      [
        15.0,
        4.0
      ],
      [
        15.0,
        3.0
      ],
      [
        15.0,
        2.0
      ],
      [
        15.0,
        1.0
      ]
    ]
  },
  {
    "u": 6,
    "v": 7,
    "key": 0,
    "length": 93.07106781186548,
    "healed": false,
    "geometry": [
      [
        18.0,
        12.0
      ],
      [
        19.0,
        12.0
      ],
      [
        20.0,
        12.0
      ],
      [
        21.0,
        12.0
      ],
      [
        22.0,
        12.0
      ],
      [
        23.0,
        12.0
      ],
      [
        24.0,
        12.0
      ],
      [
        25.0,
        12.0
      ],
      [
        26.0,
        12.0
      ],
      [
        27.0,
        12.0
      ],
      [
        28.0,
        12.0
      ],
      [
        29.0,
        12.0
      ],
      [
        30.0,
        12.0
      ],
      [
        31.0,
        12.0
      ],
      [
        32.0,
        12.0
      ],
      [
        33.0,
        12.0
      ],
      [
        34.0,
        12.0
      ],
      [
        35.0,
        12.0
      ],
      [
        36.0,
        12.0
      ],
      [
        37.0,
        12.0
      ],
      [
        38.0,
        12.0
      ],
      [
        39.0,
        12.0
      ],
      [
        40.0,
        12.0
      ],
      [
        41.0,
        12.0
      ],
      [
        42.0,
        12.0
      ],
      [
        43.0,
        12.0
      ],
      [
        44.0,
        12.0
      ],
      [
        45.0,
        12.0
      ],
      [
        46.0,
        12.0
      ],
      [
        47.0,
        12.0
      ],
      [
        48.0,
        12.0
      ],
      [
        49.0,
        12.0
      ],
      [
        50.0,
        12.0
      ],
      [
        51.0,
        11.0
      ],
      [
        52.0,
        11.0
      ],
      [
        53.0,
        11.0
      ],
      [
        54.0,
        11.0
      ],
      [
        55.0,
        11.0
      ],
      [
        56.0,
        11.0
      ],
      [
        57.0,
        11.0
      ],
      [
        58.0,
        11.0
      ],
      [
        59.0,
        11.0
      ],
      [
        60.0,
        11.0
      ],
      [
        61.0,
        11.0
      ],
      [
        62.0,
        11.0
      ],
      [
        63.0,
        10.0
      ],
      [
        64.0,
        10.0
      ],
      [
        65.0,
        10.0
      ],
      [
        66.0,
        10.0
      ],
      [
        67.0,
        10.0
      ],
      [
        68.0,
        10.0
      ],
      [
        69.0,
        10.0
      ],
      [
        70.0,
        10.0
      ],
      [
        71.0,
        10.0
      ],
      [
        72.0,
        10.0
      ],
      [
        73.0,
        10.0
      ],
      [
        74.0,
        10.0
      ],
      [
        75.0,
        10.0
      ],
      [
        76.0,
        10.0
      ],
      [
        77.0,
        10.0
      ],
      [
        78.0,
        10.0
      ],
      [
        79.0,
        10.0
      ],
      [
        80.0,
        10.0
      ],
      [
        81.0,
        10.0
      ],
      [
        82.0,
        10.0
      ],
      [
        83.0,
        10.0
      ],
      [
        84.0,
        10.0
      ],
      [
        85.0,
        10.0
      ],
      [
        86.0,
        10.0
      ],
      [
        87.0,
        10.0
      ],
      [
        88.0,
        10.0
      ],
      [
        89.0,
        10.0
      ],
      [
        90.0,
        10.0
      ],
      [
        91.0,
        10.0
      ],
      [
        92.0,
        9.0
      ],
      [
        93.0,
        9.0
      ],
      [
        94.0,
        9.0
      ],
      [
        95.0,
        9.0
      ],
      [
        96.0,
        9.0
      ],
      [
        97.0,
        9.0
      ],
      [
        98.0,
        9.0
      ],
      [
        99.0,
        9.0
      ],
      [
        100.0,
        9.0
      ],
      [
        101.0,
        9.0
      ],
      [
        102.0,
        9.0
      ],
      [
        103.0,
        9.0
      ],
      [
        104.0,
        9.0
      ],
      [
        105.0,
        10.0
      ],
      [
        106.0,
        10.0
      ],
      [
        107.0,
        10.0
      ],
      [
        108.0,
        10.0
      ],
      [
        109.0,
        11.0
      ]
    ]
  },
  {
    "u": 7,
    "v": 8,
    "key": 0,
    "length": 159.24264068711926,
    "healed": false,
    "geometry": [
      [
        109.0,
        11.0
      ],
      [
        109.0,
        12.0
      ],
      [
        109.0,
        13.0
      ],
      [
        109.0,
        14.0
      ],
      [
        109.0,
        15.0
      ],
      [
        109.0,
        16.0
      ],
      [
        109.0,
        17.0
      ],
      [
        109.0,
        18.0
      ],
      [
        109.0,
        19.0
      ],
      [
        109.0,
        20.0
      ],
      [
        109.0,
        21.0
      ],
      [
        109.0,
        22.0
      ],
      [
        109.0,
        23.0
      ],
      [
        109.0,
        24.0
      ],
      [
        109.0,
        25.0
      ],
      [
        109.0,
        26.0
      ],
      [
        109.0,
        27.0
      ],
      [
        109.0,
        28.0
      ],
      [
        109.0,
        29.0
      ],
      [
        109.0,
        30.0
      ],
      [
        109.0,
        31.0
      ],
      [
        109.0,
        32.0
      ],
      [
        109.0,
        33.0
      ],
      [
        109.0,
        34.0
      ],
      [
        109.0,
        35.0
      ],
      [
        109.0,
        36.0
      ],
      [
        109.0,
        37.0
      ],
      [
        109.0,
        38.0
      ],
      [
        109.0,
        39.0
      ],
      [
        109.0,
        40.0
      ],
      [
        109.0,
        41.0
      ],
      [
        109.0,
        42.0
      ],
      [
        109.0,
        43.0
      ],
      [
        110.0,
        44.0
      ],
      [
        110.0,
        45.0
      ],
      [
        110.0,
        46.0
      ],
      [
        110.0,
        47.0
      ],
      [
        110.0,
        48.0
      ],
      [
        110.0,
        49.0
      ],
      [
        110.0,
        50.0
      ],
      [
        110.0,
        51.0
      ],
      [
        110.0,
        52.0
      ],
      [
        110.0,
        53.0
      ],
      [
        110.0,
        54.0
      ],
      [
        110.0,
        55.0
      ],
      [
        110.0,
        56.0
      ],
      [
        110.0,
        57.0
      ],
      [
        110.0,
        58.0
      ],
      [
        110.0,
        59.0
      ],
      [
        110.0,
        60.0
      ],
      [
        110.0,
        61.0
      ],
      [
        110.0,
        62.0
      ],
      [
        110.0,
        63.0
      ],
      [
        110.0,
        64.0
      ],
      [
        110.0,
        65.0
      ],
      [
        110.0,
        66.0
      ],
      [
        110.0,
        67.0
      ],
      [
        110.0,
        68.0
      ],
      [
        110.0,
        69.0
      ],
      [
        110.0,
        70.0
      ],
      [
        110.0,
        71.0
      ],
      [
        110.0,
        72.0
      ],
      [
        110.0,
        73.0
      ],
      [
        110.0,
        74.0
      ],
      [
        110.0,
        75.0
      ],
      [
        110.0,
        76.0
      ],
      [
        110.0,
        77.0
      ],
      [
        110.0,
        78.0
      ],
      [
        110.0,
        79.0
      ],
      [
        110.0,
        80.0
      ],
      [
        110.0,
        81.0
      ],
      [
        110.0,
        82.0
      ],
      [
        110.0,
        83.0
      ],
      [
        110.0,
        84.0
      ],
      [
        110.0,
        85.0
      ],
      [
        110.0,
        86.0
      ],
      [
        110.0,
        87.0
      ],
      [
        110.0,
        88.0
      ],
      [
        109.0,
        89.0
      ],
      [
        109.0,
        90.0
      ],
      [
        109.0,
        91.0
      ],
      [
        109.0,
        92.0
      ],
      [
        109.0,
        93.0
      ],
      [
        109.0,
        94.0
      ],
      [
        109.0,
        95.0
      ],
      [
        109.0,
        96.0
      ],
      [
        109.0,
        97.0
      ],
      [
        109.0,
        98.0
      ],
      [
        109.0,
        99.0
      ],
      [
        109.0,
        100.0
      ],
      [
        109.0,
        101.0
      ],
      [
        109.0,
        102.0
      ],
      [
        109.0,
        103.0
      ],
      [
        109.0,
        104.0
      ],
      [
        109.0,
        105.0
      ],
      [
        109.0,
        106.0
      ],
      [
        109.0,
        107.0
      ],
      [
        109.0,
        108.0
      ],
      [
        109.0,
        109.0
      ],
      [
        109.0,
        110.0
      ],
      [
        109.0,
        111.0
      ],
      [
        109.0,
        112.0
      ],
      [
        109.0,
        113.0
      ],
      [
        109.0,
        114.0
      ],
      [
        109.0,
        115.0
      ],
      [
        109.0,
        116.0
      ],
      [
        109.0,
        117.0
      ],
      [
        109.0,
        118.0
      ],
      [
        109.0,
        119.0
      ],
      [
        109.0,
        120.0
      ],
      [
        109.0,
        121.0
      ],
      [
        109.0,
        122.0
      ],
      [
        109.0,
        123.0
      ],
      [
        109.0,
        124.0
      ],
      [
        109.0,
        125.0
      ],
      [
        109.0,
        126.0
      ],
      [
        109.0,
        127.0
      ],
      [
        109.0,
        128.0
      ],
      [
        109.0,
        129.0
      ],
      [
        109.0,
        130.0
      ],
      [
        109.0,
        131.0
      ],
      [
        109.0,
        132.0
      ],
      [
        109.0,
        133.0
      ],
      [
        109.0,
        134.0
      ],
      [
        109.0,
        135.0
      ],
      [
        109.0,
        136.0
      ],
      [
        109.0,
        137.0
      ],
      [
        109.0,
        138.0
      ],
      [
        109.0,
        139.0
      ],
      [
        110.0,
        140.0
      ],
      [
        110.0,
        141.0
      ],
      [
        110.0,
        142.0
      ],
      [
        110.0,
        143.0
      ],
      [
        110.0,
        144.0
      ],
      [
        110.0,
        145.0
      ],
      [
        110.0,
        146.0
      ],
      [
        110.0,
        147.0
      ],
      [
        110.0,
        148.0
      ],
      [
        110.0,
        149.0
      ],
      [
        110.0,
        150.0
      ],
      [
        110.0,
        151.0
      ],
      [
        110.0,
        152.0
      ],
      [
        110.0,
        153.0
      ],
      [
        110.0,
        154.0
      ],
      [
        110.0,
        155.0
      ],
      [
        110.0,
        156.0
      ],
      [
        110.0,
        157.0
      ],
      [
        110.0,
        158.0
      ],
      [
        110.0,
        159.0
      ],
      [
        110.0,
        160.0
      ],
      [
        110.0,
        161.0
      ],
      [
        110.0,
        162.0
      ],
      [
        110.0,
        163.0
      ],
      [
        110.0,
        164.0
      ],
      [
        110.0,
        165.0
      ],
      [
        110.0,
        166.0
      ],
      [
        110.0,
        167.0
      ],
      [
        110.0,
        168.0
      ],
      [
        110.0,
        169.0
      ]
    ]
  },
  {
    "u": 7,
    "v": 9,
    "key": 0,
    "length": 57.24264068711929,
    "healed": false,
    "geometry": [
      [
        109.0,
        11.0
      ],
      [
        110.0,
        10.0
      ],
      [
        111.0,
        10.0
      ],
      [
        112.0,
        10.0
      ],
      [
        113.0,
        10.0
      ],
      [
        114.0,
        10.0
      ],
      [
        115.0,
        10.0
      ],
      [
        116.0,
        10.0
      ],
      [
        117.0,
        10.0
      ],
      [
        118.0,
        10.0
      ],
      [
        119.0,
        10.0
      ],
      [
        120.0,
        10.0
      ],
      [
        121.0,
        10.0
      ],
      [
        122.0,
        10.0
      ],
      [
        123.0,
        10.0
      ],
      [
        124.0,
        10.0
      ],
      [
        125.0,
        10.0
      ],
      [
        126.0,
        10.0
      ],
      [
        127.0,
        10.0
      ],
      [
        128.0,
        10.0
      ],
      [
        129.0,
        10.0
      ],
      [
        130.0,
        10.0
      ],
      [
        131.0,
        9.0
      ],
      [
        132.0,
        9.0
      ],
      [
        133.0,
        9.0
      ],
      [
        134.0,
        9.0
      ],
      [
        135.0,
        9.0
      ],
      [
        136.0,
        9.0
      ],
      [
        137.0,
        9.0
      ],
      [
        138.0,
        9.0
      ],
      [
        139.0,
        9.0
      ],
      [
        140.0,
        9.0
      ],
      [
        141.0,
        9.0
      ],
      [
        142.0,
        9.0
      ],
      [
        143.0,
        9.0
      ],
      [
        144.0,
        9.0
      ],
      [
        145.0,
        9.0
      ],
      [
        146.0,
        9.0
      ],
      [
        147.0,
        9.0
      ],
      [
        148.0,
        9.0
      ],
      [
        149.0,
        9.0
      ],
      [
        150.0,
        9.0
      ],
      [
        151.0,
        9.0
      ],
      [
        152.0,
        9.0
      ],
      [
        153.0,
        9.0
      ],
      [
        154.0,
        9.0
      ],
      [
        155.0,
        9.0
      ],
      [
        156.0,
        9.0
      ],
      [
        157.0,
        9.0
      ],
      [
        158.0,
        10.0
      ],
      [
        159.0,
        10.0
      ],
      [
        160.0,
        10.0
      ],
      [
        161.0,
        10.0
      ],
      [
        162.0,
        10.0
      ],
      [
        163.0,
        10.0
      ],
      [
        164.0,
        10.0
      ],
      [
        165.0,
        10.0
      ]
    ]
  },
  {
    "u": 8,
    "v": 12,
    "key": 0,
    "length": 177.38477631085024,
    "healed": false,
    "geometry": [
      [
        111.0,
        170.0
      ],
      [
        112.0,
        171.0
      ],
      [
        113.0,
        171.0
      ],
      [
        114.0,
        171.0
      ],
      [
        115.0,
        171.0
      ],
      [
        116.0,
        171.0
      ],
      [
        117.0,
        171.0
      ],
      [
        118.0,
        171.0
      ],
      [
        119.0,
        171.0
      ],
      [
        120.0,
        171.0
      ],
      [
        121.0,
        171.0
      ],
      [
        122.0,
        171.0
      ],
      [
        123.0,
        171.0
      ],
      [
        124.0,
        171.0
      ],
      [
        125.0,
        171.0
      ],
      [
        126.0,
        171.0
      ],
      [
        127.0,
        171.0
      ],
      [
        128.0,
        171.0
      ],
      [
        129.0,
        171.0
      ],
      [
        130.0,
        171.0
      ],
      [
        131.0,
        171.0
      ],
      [
        132.0,
        171.0
      ],
      [
        133.0,
        171.0
      ],
      [
        134.0,
        171.0
      ],
      [
        135.0,
        171.0
      ],
      [
        136.0,
        171.0
      ],
      [
        137.0,
        171.0
      ],
      [
        138.0,
        171.0
      ],
      [
        139.0,
        171.0
      ],
      [
        140.0,
        171.0
      ],
      [
        141.0,
        171.0
      ],
      [
        142.0,
        171.0
      ],
      [
        143.0,
        171.0
      ],
      [
        144.0,
        171.0
      ],
      [
        145.0,
        171.0
      ],
      [
        146.0,
        171.0
      ],
      [
        147.0,
        171.0
      ],
      [
        148.0,
        171.0
      ],
      [
        149.0,
        171.0
      ],
      [
        150.0,
        171.0
      ],
      [
        151.0,
        171.0
      ],
      [
        152.0,
        171.0
      ],
      [
        153.0,
        171.0
      ],
      [
        154.0,
        171.0
      ],
      [
        155.0,
        171.0
      ],
      [
        156.0,
        171.0
      ],
      [
        157.0,
        171.0
      ],
      [
        158.0,
        171.0
      ],
      [
        159.0,
        171.0
      ],
      [
        160.0,
        171.0
      ],
      [
        161.0,
        171.0
      ],
      [
        162.0,
        171.0
      ],
      [
        163.0,
        171.0
      ],
      [
        164.0,
        171.0
      ],
      [
        165.0,
        171.0
      ],
      [
        166.0,
        171.0
      ],
      [
        167.0,
        171.0
      ],
      [
        168.0,
        171.0
      ],
      [
        169.0,
        171.0
      ],
      [
        170.0,
        171.0
      ],
      [
        171.0,
        170.0
      ],
      [
        172.0,
        170.0
      ],
      [
        173.0,
        170.0
      ],
      [
        174.0,
        170.0
      ],
      [
        175.0,
        170.0
      ],
      [
        176.0,
        170.0
      ],
      [
        177.0,
        170.0
      ],
      [
        178.0,
        170.0
      ],
      [
        179.0,
        170.0
      ],
      [
        180.0,
        170.0
      ],
      [
        181.0,
        170.0
      ],
      [
        182.0,
        170.0
      ],
      [
        183.0,
        170.0
      ],
      [
        184.0,
        170.0
      ],
      [
        185.0,
        170.0
      ],
      [
        186.0,
        170.0
      ],
      [
        187.0,
        170.0
      ],
      [
        188.0,
        170.0
      ],
      [
        189.0,
        170.0
      ],
      [
        190.0,
        169.0
      ],
      [
        191.0,
        169.0
      ],
      [
        192.0,
        169.0
      ],
      [
        193.0,
        169.0
      ],
      [
        194.0,
        169.0
      ],
      [
        195.0,
        169.0
      ],
      [
        196.0,
        169.0
      ],
      [
        197.0,
        169.0
      ],
      [
        198.0,
        169.0
      ],
      [
        199.0,
        169.0
      ],
      [
        200.0,
        169.0
      ],
      [
        201.0,
        168.0
      ],
      [
        202.0,
        167.0
      ],
      [
        203.0,
        166.0
      ],
      [
        203.0,
        165.0
      ],
      [
        203.0,
        164.0
      ],
      [
        203.0,
        163.0
      ],
      [
        203.0,
        162.0
      ],
      [
        203.0,
        161.0
      ],
      [
        204.0,
        160.0
      ],
      [
        204.0,
        159.0
      ],
      [
        204.0,
        158.0
      ],
      [
        203.0,
        157.0
      ],
      [
        203.0,
        156.0
      ],
      [
        203.0,
        155.0
      ],
      [
        203.0,
        154.0
      ],
      [
        203.0,
        153.0
      ],
      [
        204.0,
        152.0
      ],
      [
        204.0,
        151.0
      ],
      [
        204.0,
        150.0
      ],
      [
        204.0,
        149.0
      ],
      [
        204.0,
        148.0
      ],
      [
        204.0,
        147.0
      ],
      [
        204.0,
        146.0
      ],
      [
        204.0,
        145.0
      ],
      [
        204.0,
        144.0
      ],
      [
        204.0,
        143.0
      ],
      [
        204.0,
        142.0
      ],
      [
        204.0,
        141.0
      ],
      [
        204.0,
        140.0
      ],
      [
        204.0,
        139.0
      ],
      [
        204.0,
        138.0
      ],
      [
        204.0,
        137.0
      ],
      [
        204.0,
        136.0
      ],
      [
        204.0,
        135.0
      ],
      [
        204.0,
        134.0
      ],
      [
        204.0,
        133.0
      ],
      [
        204.0,
        132.0
      ],
      [
        204.0,
        131.0
      ],
      [
        204.0,
        130.0
      ],
      [
        204.0,
        129.0
      ],
      [
        204.0,
        128.0
      ],
      [
        205.0,
        127.0
      ],
      [
        205.0,
        126.0
      ],
      [
        204.0,
        125.0
      ],
      [
        204.0,
        124.0
      ],
      [
        204.0,
        123.0
      ],
      [
        204.0,
        122.0
      ],
      [
        204.0,
        121.0
      ],
      [
        204.0,
        120.0
      ],
      [
        204.0,
        119.0
      ],
      [
        204.0,
        118.0
      ],
      [
        204.0,
        117.0
      ],
      [
        204.0,
        116.0
      ],
      [
        204.0,
        115.0
      ],
      [
        204.0,
        114.0
      ],
      [
        204.0,
        113.0
      ],
      [
        204.0,
        112.0
      ],
      [
        204.0,
        111.0
      ],
      [
        205.0,
        110.0
      ],
      [
        205.0,
        109.0
      ],
      [
        205.0,
        108.0
      ],
      [
        205.0,
        107.0
      ],
      [
        205.0,
        106.0
      ],
      [
        205.0,
        105.0
      ],
      [
        205.0,
        104.0
      ],
      [
        205.0,
        103.0
      ],
      [
        205.0,
        102.0
      ],
      [
        205.0,
        101.0
      ],
      [
        205.0,
        100.0
      ],
      [
        205.0,
        99.0
      ],
      [
        205.0,
        98.0
      ],
      [
        205.0,
        97.0
      ],
      [
        205.0,
        96.0
      ],
      [
        205.0,
        95.0
      ],
      [
        205.0,
        94.0
      ],
      [
        205.0,
        93.0
      ],
      [
        205.0,
        92.0
      ],
      [
        205.0,
        91.0
      ],
      [
        205.0,
        90.0
      ],
      [
        205.0,
        89.0
      ],
      [
        205.0,
        88.0
      ],
      [
        206.0,
        87.0
      ],
      [
        206.0,
        86.0
      ]
    ]
  },
  {
    "u": 9,
    "v": 18,
    "key": 0,
    "length": 8.414213562373096,
    "healed": false,
    "geometry": [
      [
        166.0,
        11.0
      ],
      [
        166.0,
        12.0
      ],
      [
        166.0,
        13.0
      ],
      [
        166.0,
        14.0
      ],
      [
        166.0,
        15.0
      ],
      [
        166.0,
        16.0
      ],
      [
        165.0,
        17.0
      ],
      [
        165.0,
        18.0
      ],
      [
        165.0,
        19.0
      ]
    ]
  },
  {
    "u": 9,
    "v": 10,
    "key": 0,
    "length": 36.24264068711929,
    "healed": false,
    "geometry": [
      [
        167.0,
        10.0
      ],
      [
        168.0,
        10.0
      ],
      [
        169.0,
        10.0
      ],
      [
        170.0,
        10.0
      ],
      [
        171.0,
        10.0
      ],
      [
        172.0,
        10.0
      ],
      [
        173.0,
        10.0
      ],
      [
        174.0,
        10.0
      ],
      [
        175.0,
        10.0
      ],
      [
        176.0,
        10.0
      ],
      [
        177.0,
        10.0
      ],
      [
        178.0,
        10.0
      ],
      [
        179.0,
        10.0
      ],
      [
        180.0,
        10.0
      ],
      [
        181.0,
        10.0
      ],
      [
        182.0,
        10.0
      ],
      [
        183.0,
        10.0
      ],
      [
        184.0,
        10.0
      ],
      [
        185.0,
        10.0
      ],
      [
        186.0,
        10.0
      ],
      [
        187.0,
        10.0
      ],
      [
        188.0,
        10.0
      ],
      [
        189.0,
        10.0
      ],
      [
        190.0,
        9.0
      ],
      [
        191.0,
        9.0
      ],
      [
        192.0,
        9.0
      ],
      [
        193.0,
        9.0
      ],
      [
        194.0,
        10.0
      ],
      [
        195.0,
        9.0
      ],
      [
        196.0,
        9.0
      ],
      [
        197.0,
        9.0
      ],
      [
        198.0,
        9.0
      ],
      [
        199.0,
        9.0
      ],
      [
        200.0,
        9.0
      ],
      [
        201.0,
        9.0
      ],
      [
        202.0,
        9.0
      ]
    ]
  },
  {
    "u": 10,
    "v": 20,
    "key": 0,
    "length": 5.82842712474619,
    "healed": false,
    "geometry": [
      [
        203.0,
        8.0
      ],
      [
        203.0,
        7.0
      ],
      [
        204.0,
        6.0
      ],
      [
        204.0,
        5.0
      ],
      [
        205.0,
        4.0
      ],
      [
        205.0,
        3.0
      ]
    ]
  },
  {
    "u": 10,
    "v": 11,
    "key": 0,
    "length": 44.65685424949238,
    "healed": false,
    "geometry": [
      [
        203.0,
        10.0
      ],
      [
        204.0,
        11.0
      ],
      [
        204.0,
        12.0
      ],
      [
        204.0,
        13.0
      ],
      [
        204.0,
        14.0
      ],
      [
        205.0,
        15.0
      ],
      [
        204.0,
        16.0
      ],
      [
        204.0,
        17.0
      ],
      [
        204.0,
        18.0
      ],
      [
        204.0,
        19.0
      ],
      [
        204.0,
        20.0
      ],
      [
        204.0,
        21.0
      ],
      [
        204.0,
        22.0
      ],
      [
        204.0,
        23.0
      ],
      [
        204.0,
        24.0
      ],
      [
        204.0,
        25.0
      ],
      [
        204.0,
        26.0
      ],
      [
        204.0,
        27.0
      ],
      [
        204.0,
        28.0
      ],
      [
        204.0,
        29.0
      ],
      [
        204.0,
        30.0
      ],
      [
        204.0,
        31.0
      ],
      [
        204.0,
        32.0
      ],
      [
        204.0,
        33.0
      ],
      [
        204.0,
        34.0
      ],
      [
        204.0,
        35.0
      ],
      [
        204.0,
        36.0
      ],
      [
        204.0,
        37.0
      ],
      [
        204.0,
        38.0
      ],
      [
        204.0,
        39.0
      ],
      [
        204.0,
        40.0
      ],
      [
        204.0,
        41.0
      ],
      [
        204.0,
        42.0
      ],
      [
        204.0,
        43.0
      ],
      [
        204.0,
        44.0
      ],
      [
        204.0,
        45.0
      ],
      [
        204.0,
        46.0
      ],
      [
        204.0,
        47.0
      ],
      [
        204.0,
        48.0
      ],
      [
        204.0,
        49.0
      ],
      [
        204.0,
        50.0
      ],
      [
        203.0,
        51.0
      ],
      [
        203.0,
        52.0
      ],
      [
        203.0,
        53.0
      ]
    ]
  },
  {
    "u": 11,
    "v": 19,
    "key": 0,
    "length": 28.82842712474619,
    "healed": false,
    "geometry": [
      [
        202.0,
        54.0
      ],
      [
        201.0,
        54.0
      ],
      [
        200.0,
        54.0
      ],
      [
        199.0,
        54.0
      ],
      [
        198.0,
        54.0
      ],
      [
        197.0,
        54.0
      ],
      [
        196.0,
        54.0
      ],
      [
        195.0,
        54.0
      ],
      [
        194.0,
        54.0
      ],
      [
        193.0,
        54.0
      ],
      [
        192.0,
        54.0
      ],
      [
        191.0,
        54.0
      ],
      [
        190.0,
        54.0
      ],
      [
        189.0,
        54.0
      ],
      [
        188.0,
        54.0
      ],
      [
        187.0,
        54.0
      ],
      [
        186.0,
        54.0
      ],
      [
        185.0,
        55.0
      ],
      [
        184.0,
        55.0
      ],
      [
        183.0,
        55.0
      ],
      [
        182.0,
        55.0
      ],
      [
        181.0,
        55.0
      ],
      [
        180.0,
        55.0
      ],
      [
        179.0,
        55.0
      ],
      [
        178.0,
        55.0
      ],
      [
        177.0,
        55.0
      ],
      [
        176.0,
        54.0
      ],
      [
        175.0,
        54.0
      ],
      [
        174.0,
        54.0
      ]
    ]
  },
  {
    "u": 11,
    "v": 12,
    "key": 0,
    "length": 31.242640687119287,
    "healed": false,
    "geometry": [
      [
        203.0,
        55.0
      ],
      [
        203.0,
        56.0
      ],
      [
        203.0,
        57.0
      ],
      [
        203.0,
        58.0
      ],
      [
        204.0,
        59.0
      ],
      [
        204.0,
        60.0
      ],
      [
        204.0,
        61.0
      ],
      [
        204.0,
        62.0
      ],
      [
        204.0,
        63.0
      ],
      [
        204.0,
        64.0
      ],
      [
        204.0,
        65.0
      ],
      [
        204.0,
        66.0
      ],
      [
        204.0,
        67.0
      ],
      [
        204.0,
        68.0
      ],
      [
        204.0,
        69.0
      ],
      [
        204.0,
        70.0
      ],
      [
        204.0,
        71.0
      ],
      [
        204.0,
        72.0
      ],
      [
        204.0,
        73.0
      ],
      [
        204.0,
        74.0
      ],
      [
        204.0,
        75.0
      ],
      [
        204.0,
        76.0
      ],
      [
        204.0,
        77.0
      ],
      [
        204.0,
        78.0
      ],
      [
        205.0,
        79.0
      ],
      [
        205.0,
        80.0
      ],
      [
        205.0,
        81.0
      ],
      [
        205.0,
        82.0
      ],
      [
        205.0,
        83.0
      ],
      [
        205.0,
        84.0
      ],
      [
        206.0,
        85.0
      ]
    ]
  },
  {
    "u": 12,
    "v": 14,
    "key": 0,
    "length": 120.89949493661166,
    "healed": false,
    "geometry": [
      [
        207.0,
        85.0
      ],
      [
        208.0,
        85.0
      ],
      [
        209.0,
        85.0
      ],
      [
        210.0,
        85.0
      ],
      [
        211.0,
        85.0
      ],
      [
        212.0,
        85.0
      ],
      [
        213.0,
        85.0
      ],
      [
        214.0,
        85.0
      ],
      [
        215.0,
        86.0
      ],
      [
        216.0,
        86.0
      ],
      [
        217.0,
        86.0
      ],
      [
        218.0,
        86.0
      ],
      [
        219.0,
        86.0
      ],
      [
        220.0,
        86.0
      ],
      [
        221.0,
        86.0
      ],
      [
        222.0,
        86.0
      ],
      [
        223.0,
        86.0
      ],
      [
        224.0,
        86.0
      ],
      [
        225.0,
        86.0
      ],
      [
        226.0,
        86.0
      ],
      [
        227.0,
        86.0
      ],
      [
        228.0,
        86.0
      ],
      [
        229.0,
        86.0
      ],
      [
        230.0,
        86.0
      ],
      [
        231.0,
        86.0
      ],
      [
        232.0,
        86.0
      ],
      [
        233.0,
        86.0
      ],
      [
        234.0,
        86.0
      ],
      [
        235.0,
        86.0
      ],
      [
        236.0,
        86.0
      ],
      [
        237.0,
        86.0
      ],
      [
        238.0,
        86.0
      ],
      [
        239.0,
        87.0
      ],
      [
        240.0,
        87.0
      ],
      [
        241.0,
        87.0
      ],
      [
        242.0,
        87.0
      ],
      [
        243.0,
        87.0
      ],
      [
        244.0,
        87.0
      ],
      [
        245.0,
        87.0
      ],
      [
        246.0,
        87.0
      ],
      [
        247.0,
        88.0
      ],
      [
        248.0,
        88.0
      ],
      [
        249.0,
        88.0
      ],
      [
        250.0,
        88.0
      ],
      [
        251.0,
        88.0
      ],
      [
        252.0,
        88.0
      ],
      [
        253.0,
        88.0
      ],
      [
        254.0,
        88.0
      ],
      [
        255.0,
        88.0
      ],
      [
        256.0,
        88.0
      ],
      [
        257.0,
        88.0
      ],
      [
        258.0,
        88.0
      ],
      [
        259.0,
        88.0
      ],
      [
        260.0,
        89.0
      ],
      [
        261.0,
        89.0
      ],
      [
        262.0,
        89.0
      ],
      [
        263.0,
        89.0
      ],
      [
        264.0,
        89.0
      ],
      [
        265.0,
        89.0
      ],
      [
        266.0,
        89.0
      ],
      [
        267.0,
        89.0
      ],
      [
        268.0,
        89.0
      ],
      [
        269.0,
        89.0
      ],
      [
        270.0,
        89.0
      ],
      [
        271.0,
        89.0
      ],
      [
        272.0,
        89.0
      ],
      [
        273.0,
        89.0
      ],
      [
        274.0,
        89.0
      ],
      [
        275.0,
        89.0
      ],
      [
        276.0,
        89.0
      ],
      [
        277.0,
        88.0
      ],
      [
        278.0,
        88.0
      ],
      [
        279.0,
        88.0
      ],
      [
        280.0,
        88.0
      ],
      [
        281.0,
        88.0
      ],
      [
        282.0,
        88.0
      ],
      [
        283.0,
        88.0
      ],
      [
        284.0,
        88.0
      ],
      [
        285.0,
        88.0
      ],
      [
        286.0,
        88.0
      ],
      [
        287.0,
        88.0
      ],
      [
        288.0,
        88.0
      ],
      [
        289.0,
        88.0
      ],
      [
        290.0,
        88.0
      ],
      [
        291.0,
        88.0
      ],
      [
        292.0,
        88.0
      ],
      [
        293.0,
        88.0
      ],
      [
        294.0,
        88.0
      ],
      [
        295.0,
        88.0
      ],
      [
        296.0,
        88.0
      ],
      [
        297.0,
        88.0
      ],
      [
        298.0,
        88.0
      ],
      [
        299.0,
        88.0
      ],
      [
        300.0,
        88.0
      ],
      [
        301.0,
        88.0
      ],
      [
        302.0,
        88.0
      ],
      [
        303.0,
        88.0
      ],
      [
        304.0,
        87.0
      ],
      [
        305.0,
        87.0
      ],
      [
        306.0,
        87.0
      ],
      [
        307.0,
        87.0
      ],
      [
        308.0,
        87.0
      ],
      [
        309.0,
        87.0
      ],
      [
        310.0,
        87.0
      ],
      [
        311.0,
        87.0
      ],
      [
        312.0,
        87.0
      ],
      [
        313.0,
        87.0
      ],
      [
        314.0,
        87.0
      ],
      [
        315.0,
        86.0
      ],
      [
        316.0,
        86.0
      ],
      [
        317.0,
        86.0
      ],
      [
        318.0,
        86.0
      ],
      [
        319.0,
        86.0
      ],
      [
        320.0,
        86.0
      ],
      [
        321.0,
        86.0
      ],
      [
        322.0,
        86.0
      ],
      [
        323.0,
        86.0
      ],
      [
        324.0,
        86.0
      ],
      [
        325.0,
        86.0
      ]
    ]
  },
  {
    "u": 13,
    "v": 21,
    "key": 0,
    "length": 77.39696961966999,
    "healed": false,
    "geometry": [
      [
        317.0,
        464.0
      ],
      [
        316.0,
        464.0
      ],
      [
        315.0,
        464.0
      ],
      [
        314.0,
        465.0
      ],
      [
        313.0,
        465.0
      ],
      [
        312.0,
        465.0
      ],
      [
        311.0,
        465.0
      ],
      [
        310.0,
        466.0
      ],
      [
        309.0,
        467.0
      ],
      [
        308.0,
        468.0
      ],
      [
        307.0,
        469.0
      ],
      [
        307.0,
        470.0
      ],
      [
        306.0,
        471.0
      ],
      [
        305.0,
        472.0
      ],
      [
        305.0,
        473.0
      ],
      [
        304.0,
        474.0
      ],
      [
        303.0,
        475.0
      ],
      [
        302.0,
        475.0
      ],
      [
        301.0,
        476.0
      ],
      [
        300.0,
        477.0
      ],
      [
        299.0,
        478.0
      ],
      [
        299.0,
        479.0
      ],
      [
        298.0,
        480.0
      ],
      [
        297.0,
        481.0
      ],
      [
        296.0,
        482.0
      ],
      [
        295.0,
        482.0
      ],
      [
        294.0,
        483.0
      ],
      [
        293.0,
        484.0
      ],
      [
        292.0,
        485.0
      ],
      [
        292.0,
        486.0
      ],
      [
        291.0,
        487.0
      ],
      [
        290.0,
        488.0
      ],
      [
        289.0,
        489.0
      ],
      [
        288.0,
        490.0
      ],
      [
        287.0,
        491.0
      ],
      [
        287.0,
        492.0
      ],
      [
        286.0,
        493.0
      ],
      [
        285.0,
        494.0
      ],
      [
        284.0,
        495.0
      ],
      [
        283.0,
        496.0
      ],
      [
        282.0,
        497.0
      ],
      [
        281.0,
        498.0
      ],
      [
        280.0,
        499.0
      ],
      [
        279.0,
        500.0
      ],
      [
        278.0,
        501.0
      ],
      [
        277.0,
        502.0
      ],
      [
        276.0,
        503.0
      ],
      [
        275.0,
        504.0
      ],
      [
        274.0,
        505.0
      ],
      [
        273.0,
        506.0
      ],
      [
        272.0,
        507.0
      ],
      [
        271.0,
        507.0
      ],
      [
        270.0,
        508.0
      ],
      [
        269.0,
        508.0
      ],
      [
        268.0,
        509.0
      ],
      [
        267.0,
        509.0
      ],
      [
        266.0,
        509.0
      ],
      [
        265.0,
        509.0
      ],
      [
        264.0,
        510.0
      ],
      [
        263.0,
        511.0
      ],
      [
        262.0,
        511.0
      ]
    ]
  },
  {
    "u": 13,
    "v": 25,
    "key": 0,
    "length": 305.2863632885151,
    "healed": false,
    "geometry": [
      [
        318.0,
        463.0
      ],
      [
        318.0,
        462.0
      ],
      [
        318.0,
        461.0
      ],
      [
        319.0,
        460.0
      ],
      [
        319.0,
        459.0
      ],
      [
        320.0,
        458.0
      ],
      [
        320.0,
        457.0
      ],
      [
        321.0,
        456.0
      ],
      [
        322.0,
        455.0
      ],
      [
        322.0,
        454.0
      ],
      [
        323.0,
        453.0
      ],
      [
        323.0,
        452.0
      ],
      [
        324.0,
        451.0
      ],
      [
        325.0,
        450.0
      ],
      [
        326.0,
        449.0
      ],
      [
        326.0,
        448.0
      ],
      [
        327.0,
        447.0
      ],
      [
        328.0,
        446.0
      ],
      [
        329.0,
        445.0
      ],
      [
        329.0,
        444.0
      ],
      [
        330.0,
        443.0
      ],
      [
        331.0,
        442.0
      ],
      [
        332.0,
        441.0
      ],
      [
        333.0,
        440.0
      ],
      [
        334.0,
        439.0
      ],
      [
        335.0,
        438.0
      ],
      [
        335.0,
        437.0
      ],
      [
        336.0,
        436.0
      ],
      [
        337.0,
        435.0
      ],
      [
        338.0,
        434.0
      ],
      [
        339.0,
        433.0
      ],
      [
        340.0,
        432.0
      ],
      [
        341.0,
        431.0
      ],
      [
        342.0,
        430.0
      ],
      [
        343.0,
        429.0
      ],
      [
        344.0,
        428.0
      ],
      [
        345.0,
        427.0
      ],
      [
        346.0,
        426.0
      ],
      [
        346.0,
        425.0
      ],
      [
        347.0,
        424.0
      ],
      [
        348.0,
        423.0
      ],
      [
        349.0,
        422.0
      ],
      [
        350.0,
        421.0
      ],
      [
        351.0,
        420.0
      ],
      [
        352.0,
        419.0
      ],
      [
        353.0,
        418.0
      ],
      [
        354.0,
        417.0
      ],
      [
        355.0,
        416.0
      ],
      [
        356.0,
        415.0
      ],
      [
        357.0,
        414.0
      ],
      [
        358.0,
        413.0
      ],
      [
        358.0,
        412.0
      ],
      [
        359.0,
        411.0
      ],
      [
        360.0,
        410.0
      ],
      [
        361.0,
        409.0
      ],
      [
        362.0,
        408.0
      ],
      [
        362.0,
        407.0
      ],
      [
        363.0,
        406.0
      ],
      [
        364.0,
        405.0
      ],
      [
        365.0,
        404.0
      ],
      [
        366.0,
        403.0
      ],
      [
        367.0,
        402.0
      ],
      [
        367.0,
        401.0
      ],
      [
        368.0,
        400.0
      ],
      [
        369.0,
        399.0
      ],
      [
        370.0,
        399.0
      ],
      [
        371.0,
        398.0
      ],
      [
        371.0,
        397.0
      ],
      [
        372.0,
        396.0
      ],
      [
        373.0,
        395.0
      ],
      [
        374.0,
        394.0
      ],
      [
        375.0,
        393.0
      ],
      [
        376.0,
        392.0
      ],
      [
        376.0,
        391.0
      ],
      [
        377.0,
        390.0
      ],
      [
        378.0,
        389.0
      ],
      [
        379.0,
        388.0
      ],
      [
        380.0,
        387.0
      ],
      [
        381.0,
        386.0
      ],
      [
        382.0,
        385.0
      ],
      [
        382.0,
        384.0
      ],
      [
        383.0,
        383.0
      ],
      [
        384.0,
        382.0
      ],
      [
        385.0,
        381.0
      ],
      [
        386.0,
        380.0
      ],
      [
        387.0,
        379.0
      ],
      [
        387.0,
        378.0
      ],
      [
        388.0,
        377.0
      ],
      [
        389.0,
        376.0
      ],
      [
        390.0,
        375.0
      ],
      [
        391.0,
        374.0
      ],
      [
        392.0,
        373.0
      ],
      [
        393.0,
        372.0
      ],
      [
        394.0,
        371.0
      ],
      [
        395.0,
        370.0
      ],
      [
        396.0,
        369.0
      ],
      [
        397.0,
        368.0
      ],
      [
        398.0,
        367.0
      ],
      [
        399.0,
        366.0
      ],
      [
        400.0,
        365.0
      ],
      [
        401.0,
        364.0
      ],
      [
        402.0,
        363.0
      ],
      [
        402.0,
        362.0
      ],
      [
        403.0,
        361.0
      ],
      [
        404.0,
        360.0
      ],
      [
        404.0,
        359.0
      ],
      [
        405.0,
        358.0
      ],
      [
        406.0,
        357.0
      ],
      [
        407.0,
        356.0
      ],
      [
        408.0,
        355.0
      ],
      [
        409.0,
        354.0
      ],
      [
        410.0,
        353.0
      ],
      [
        411.0,
        353.0
      ],
      [
        412.0,
        352.0
      ],
      [
        413.0,
        351.0
      ],
      [
        414.0,
        350.0
      ],
      [
        415.0,
        349.0
      ],
      [
        416.0,
        348.0
      ],
      [
        417.0,
        347.0
      ],
      [
        418.0,
        346.0
      ],
      [
        419.0,
        345.0
      ],
      [
        420.0,
        344.0
      ],
      [
        421.0,
        343.0
      ],
      [
        421.0,
        342.0
      ],
      [
        422.0,
        341.0
      ],
      [
        423.0,
        340.0
      ],
      [
        424.0,
        339.0
      ],
      [
        425.0,
        338.0
      ],
      [
        426.0,
        337.0
      ],
      [
        427.0,
        336.0
      ],
      [
        428.0,
        335.0
      ],
      [
        429.0,
        334.0
      ],
      [
        430.0,
        333.0
      ],
      [
        431.0,
        332.0
      ],
      [
        432.0,
        331.0
      ],
      [
        433.0,
        330.0
      ],
      [
        434.0,
        329.0
      ],
      [
        435.0,
        328.0
      ],
      [
        436.0,
        328.0
      ],
      [
        437.0,
        327.0
      ],
      [
        437.0,
        326.0
      ],
      [
        438.0,
        325.0
      ],
      [
        439.0,
        324.0
      ],
      [
        440.0,
        323.0
      ],
      [
        441.0,
        322.0
      ],
      [
        442.0,
        321.0
      ],
      [
        443.0,
        320.0
      ],
      [
        444.0,
        319.0
      ],
      [
        444.0,
        318.0
      ],
      [
        445.0,
        317.0
      ],
      [
        446.0,
        316.0
      ],
      [
        447.0,
        315.0
      ],
      [
        447.0,
        314.0
      ],
      [
        448.0,
        313.0
      ],
      [
        449.0,
        312.0
      ],
      [
        450.0,
        312.0
      ],
      [
        451.0,
        311.0
      ],
      [
        452.0,
        310.0
      ],
      [
        452.0,
        309.0
      ],
      [
        453.0,
        308.0
      ],
      [
        454.0,
        307.0
      ],
      [
        455.0,
        306.0
      ],
      [
        456.0,
        305.0
      ],
      [
        457.0,
        304.0
      ],
      [
        458.0,
        303.0
      ],
      [
        459.0,
        302.0
      ],
      [
        460.0,
        301.0
      ],
      [
        461.0,
        300.0
      ],
      [
        462.0,
        299.0
      ],
      [
        462.0,
        298.0
      ],
      [
        463.0,
        297.0
      ],
      [
        464.0,
        296.0
      ],
      [
        465.0,
        295.0
      ],
      [
        466.0,
        294.0
      ],
      [
        466.0,
        293.0
      ],
      [
        467.0,
        292.0
      ],
      [
        468.0,
        291.0
      ],
      [
        469.0,
        290.0
      ],
      [
        470.0,
        289.0
      ],
      [
        471.0,
        288.0
      ],
      [
        472.0,
        287.0
      ],
      [
        472.0,
        286.0
      ],
      [
        473.0,
        285.0
      ],
      [
        474.0,
        284.0
      ],
      [
        475.0,
        283.0
      ],
      [
        476.0,
        282.0
      ],
      [
        477.0,
        281.0
      ],
      [
        478.0,
        280.0
      ],
      [
        479.0,
        279.0
      ],
      [
        480.0,
        278.0
      ],
      [
        480.0,
        277.0
      ],
      [
        481.0,
        276.0
      ],
      [
        482.0,
        275.0
      ],
      [
        483.0,
        274.0
      ],
      [
        484.0,
        273.0
      ],
      [
        485.0,
        272.0
      ],
      [
        486.0,
        271.0
      ],
      [
        487.0,
        270.0
      ],
      [
        488.0,
        269.0
      ],
      [
        488.0,
        268.0
      ],
      [
        489.0,
        267.0
      ],
      [
        490.0,
        266.0
      ],
      [
        491.0,
        265.0
      ],
      [
        492.0,
        264.0
      ],
      [
        493.0,
        263.0
      ],
      [
        494.0,
        262.0
      ],
      [
        495.0,
        261.0
      ],
      [
        496.0,
        260.0
      ],
      [
        496.0,
        259.0
      ],
      [
        497.0,
        258.0
      ],
      [
        498.0,
        257.0
      ],
      [
        499.0,
        256.0
      ],
      [
        499.0,
        255.0
      ],
      [
        500.0,
        254.0
      ],
      [
        501.0,
        253.0
      ],
      [
        502.0,
        252.0
      ],
      [
        503.0,
        251.0
      ],
      [
        504.0,
        250.0
      ],
      [
        505.0,
        249.0
      ],
      [
        506.0,
        248.0
      ],
      [
        507.0,
        247.0
      ],
      [
        508.0,
        246.0
      ],
      [
        508.0,
        245.0
      ],
      [
        509.0,
        244.0
      ],
      [
        509.0,
        243.0
      ],
      [
        510.0,
        242.0
      ],
      [
        510.0,
        241.0
      ],
      [
        511.0,
        240.0
      ]
    ]
  },
  {
    "u": 13,
    "v": 22,
    "key": 0,
    "length": 48.07106781186547,
    "healed": false,
    "geometry": [
      [
        318.0,
        465.0
      ],
      [
        319.0,
        466.0
      ],
      [
        319.0,
        467.0
      ],
      [
        319.0,
        468.0
      ],
      [
        320.0,
        469.0
      ],
      [
        320.0,
        470.0
      ],
      [
        320.0,
        471.0
      ],
      [
        320.0,
        472.0
      ],
      [
        320.0,
        473.0
      ],
      [
        320.0,
        474.0
      ],
      [
        320.0,
        475.0
      ],
      [
        320.0,
        476.0
      ],
      [
        320.0,
        477.0
      ],
      [
        320.0,
        478.0
      ],
      [
        320.0,
        479.0
      ],
      [
        320.0,
        480.0
      ],
      [
        320.0,
        481.0
      ],
      [
        320.0,
        482.0
      ],
      [
        320.0,
        483.0
      ],
      [
        320.0,
        484.0
      ],
      [
        320.0,
        485.0
      ],
      [
        320.0,
        486.0
      ],
      [
        320.0,
        487.0
      ],
      [
        320.0,
        488.0
      ],
      [
        320.0,
        489.0
      ],
      [
        320.0,
        490.0
      ],
      [
        320.0,
        491.0
      ],
      [
        320.0,
        492.0
      ],
      [
        320.0,
        493.0
      ],
      [
        320.0,
        494.0
      ],
      [
        320.0,
        495.0
      ],
      [
        320.0,
        496.0
      ],
      [
        320.0,
        497.0
      ],
      [
        320.0,
        498.0
      ],
      [
        320.0,
        499.0
      ],
      [
        320.0,
        500.0
      ],
      [
        320.0,
        501.0
      ],
      [
        320.0,
        502.0
      ],
      [
        320.0,
        503.0
      ],
      [
        320.0,
        504.0
      ],
      [
        320.0,
        505.0
      ],
      [
        320.0,
        506.0
      ],
      [
        320.0,
        507.0
      ],
      [
        320.0,
        508.0
      ],
      [
        321.0,
        509.0
      ],
      [
        322.0,
        510.0
      ],
      [
        323.0,
        511.0
      ]
    ]
  },
  {
    "u": 14,
    "v": 23,
    "key": 0,
    "length": 67.07106781186548,
    "healed": false,
    "geometry": [
      [
        326.0,
        85.0
      ],
      [
        326.0,
        84.0
      ],
      [
        326.0,
        83.0
      ],
      [
        326.0,
        82.0
      ],
      [
        326.0,
        81.0
      ],
      [
        327.0,
        80.0
      ],
      [
        327.0,
        79.0
      ],
      [
        327.0,
        78.0
      ],
      [
        327.0,
        77.0
      ],
      [
        327.0,
        76.0
      ],
      [
        327.0,
        75.0
      ],
      [
        327.0,
        74.0
      ],
      [
        326.0,
        73.0
      ],
      [
        326.0,
        72.0
      ],
      [
        326.0,
        71.0
      ],
      [
        326.0,
        70.0
      ],
      [
        326.0,
        69.0
      ],
      [
        325.0,
        68.0
      ],
      [
        325.0,
        67.0
      ],
      [
        325.0,
        66.0
      ],
      [
        325.0,
        65.0
      ],
      [
        325.0,
        64.0
      ],
      [
        325.0,
        63.0
      ],
      [
        325.0,
        62.0
      ],
      [
        325.0,
        61.0
      ],
      [
        325.0,
        60.0
      ],
      [
        325.0,
        59.0
      ],
      [
        325.0,
        58.0
      ],
      [
        325.0,
        57.0
      ],
      [
        325.0,
        56.0
      ],
      [
        325.0,
        55.0
      ],
      [
        325.0,
        54.0
      ],
      [
        325.0,
        53.0
      ],
      [
        325.0,
        52.0
      ],
      [
        325.0,
        51.0
      ],
      [
        325.0,
        50.0
      ],
      [
        325.0,
        49.0
      ],
      [
        325.0,
        48.0
      ],
      [
        325.0,
        47.0
      ],
      [
        325.0,
        46.0
      ],
      [
        325.0,
        45.0
      ],
      [
        325.0,
        44.0
      ],
      [
        325.0,
        43.0
      ],
      [
        325.0,
        42.0
      ],
      [
        325.0,
        41.0
      ],
      [
        325.0,
        40.0
      ],
      [
        325.0,
        39.0
      ],
      [
        325.0,
        38.0
      ],
      [
        325.0,
        37.0
      ],
      [
        325.0,
        36.0
      ],
      [
        325.0,
        35.0
      ],
      [
        325.0,
        34.0
      ],
      [
        325.0,
        33.0
      ],
      [
        325.0,
        32.0
      ],
      [
        325.0,
        31.0
      ],
      [
        325.0,
        30.0
      ],
      [
        325.0,
        29.0
      ],
      [
        325.0,
        28.0
      ],
      [
        326.0,
        27.0
      ],
      [
        326.0,
        26.0
      ],
      [
        326.0,
        25.0
      ],
      [
        325.0,
        24.0
      ],
      [
        325.0,
        23.0
      ],
      [
        325.0,
        22.0
      ],
      [
        325.0,
        21.0
      ],
      [
        325.0,
        20.0
      ]
    ]
  },
  {
    "u": 14,
    "v": 24,
    "key": 0,
    "length": 185.31370849898477,
    "healed": false,
    "geometry": [
      [
        327.0,
        86.0
      ],
      [
        328.0,
        86.0
      ],
      [
        329.0,
        86.0
      ],
      [
        330.0,
        87.0
      ],
      [
        331.0,
        87.0
      ],
      [
        332.0,
        87.0
      ],
      [
        333.0,
        87.0
      ],
      [
        334.0,
        87.0
      ],
      [
        335.0,
        87.0
      ],
      [
        336.0,
        87.0
      ],
      [
        337.0,
        86.0
      ],
      [
        338.0,
        86.0
      ],
      [
        339.0,
        86.0
      ],
      [
        340.0,
        86.0
      ],
      [
        341.0,
        86.0
      ],
      [
        342.0,
        86.0
      ],
      [
        343.0,
        86.0
      ],
      [
        344.0,
        86.0
      ],
      [
        345.0,
        86.0
      ],
      [
        346.0,
        86.0
      ],
      [
        347.0,
        86.0
      ],
      [
        348.0,
        86.0
      ],
      [
        349.0,
        86.0
      ],
      [
        350.0,
        86.0
      ],
      [
        351.0,
        86.0
      ],
      [
        352.0,
        86.0
      ],
      [
        353.0,
        86.0
      ],
      [
        354.0,
        86.0
      ],
      [
        355.0,
        86.0
      ],
      [
        356.0,
        87.0
      ],
      [
        357.0,
        87.0
      ],
      [
        358.0,
        87.0
      ],
      [
        359.0,
        87.0
      ],
      [
        360.0,
        87.0
      ],
      [
        361.0,
        87.0
      ],
      [
        362.0,
        87.0
      ],
      [
        363.0,
        87.0
      ],
      [
        364.0,
        87.0
      ],
      [
        365.0,
        87.0
      ],
      [
        366.0,
        87.0
      ],
      [
        367.0,
        87.0
      ],
      [
        368.0,
        87.0
      ],
      [
        369.0,
        87.0
      ],
      [
        370.0,
        87.0
      ],
      [
        371.0,
        87.0
      ],
      [
        372.0,
        87.0
      ],
      [
        373.0,
        87.0
      ],
      [
        374.0,
        87.0
      ],
      [
        375.0,
        87.0
      ],
      [
        376.0,
        87.0
      ],
      [
        377.0,
        87.0
      ],
      [
        378.0,
        87.0
      ],
      [
        379.0,
        87.0
      ],
      [
        380.0,
        87.0
      ],
      [
        381.0,
        87.0
      ],
      [
        382.0,
        87.0
      ],
      [
        383.0,
        87.0
      ],
      [
        384.0,
        87.0
      ],
      [
        385.0,
        87.0
      ],
      [
        386.0,
        87.0
      ],
      [
        387.0,
        87.0
      ],
      [
        388.0,
        87.0
      ],
      [
        389.0,
        87.0
      ],
      [
        390.0,
        87.0
      ],
      [
        391.0,
        87.0
      ],
      [
        392.0,
        87.0
      ],
      [
        393.0,
        87.0
      ],
      [
        394.0,
        87.0
      ],
      [
        395.0,
        87.0
      ],
      [
        396.0,
        87.0
      ],
      [
        397.0,
        87.0
      ],
      [
        398.0,
        87.0
      ],
      [
        399.0,
        87.0
      ],
      [
        400.0,
        87.0
      ],
      [
        401.0,
        87.0
      ],
      [
        402.0,
        87.0
      ],
      [
        403.0,
        87.0
      ],
      [
        404.0,
        87.0
      ],
      [
        405.0,
        87.0
      ],
      [
        406.0,
        87.0
      ],
      [
        407.0,
        87.0
      ],
      [
        408.0,
        87.0
      ],
      [
        409.0,
        87.0
      ],
      [
        410.0,
        87.0
      ],
      [
        411.0,
        87.0
      ],
      [
        412.0,
        87.0
      ],
      [
        413.0,
        87.0
      ],
      [
        414.0,
        87.0
      ],
      [
        415.0,
        87.0
      ],
      [
        416.0,
        87.0
      ],
      [
        417.0,
        87.0
      ],
      [
        418.0,
        87.0
      ],
      [
        419.0,
        86.0
      ],
      [
        420.0,
        86.0
      ],
      [
        421.0,
        86.0
      ],
      [
        422.0,
        86.0
      ],
      [
        423.0,
        86.0
      ],
      [
        424.0,
        86.0
      ],
      [
        425.0,
        86.0
      ],
      [
        426.0,
        86.0
      ],
      [
        427.0,
        86.0
      ],
      [
        428.0,
        86.0
      ],
      [
        429.0,
        86.0
      ],
      [
        430.0,
        86.0
      ],
      [
        431.0,
        86.0
      ],
      [
        432.0,
        86.0
      ],
      [
        433.0,
        86.0
      ],
      [
        434.0,
        86.0
      ],
      [
        435.0,
        86.0
      ],
      [
        436.0,
        86.0
      ],
      [
        437.0,
        86.0
      ],
      [
        438.0,
        86.0
      ],
      [
        439.0,
        86.0
      ],
      [
        440.0,
        86.0
      ],
      [
        441.0,
        86.0
      ],
      [
        442.0,
        86.0
      ],
      [
        443.0,
        86.0
      ],
      [
        444.0,
        86.0
      ],
      [
        445.0,
        86.0
      ],
      [
        446.0,
        86.0
      ],
      [
        447.0,
        86.0
      ],
      [
        448.0,
        86.0
      ],
      [
        449.0,
        86.0
      ],
      [
        450.0,
        86.0
      ],
      [
        451.0,
        86.0
      ],
      [
        452.0,
        86.0
      ],
      [
        453.0,
        86.0
      ],
      [
        454.0,
        86.0
      ],
      [
        455.0,
        86.0
      ],
      [
        456.0,
        86.0
      ],
      [
        457.0,
        86.0
      ],
      [
        458.0,
        86.0
      ],
      [
        459.0,
        86.0
      ],
      [
        460.0,
        86.0
      ],
      [
        461.0,
        86.0
      ],
      [
        462.0,
        86.0
      ],
      [
        463.0,
        86.0
      ],
      [
        464.0,
        85.0
      ],
      [
        465.0,
        85.0
      ],
      [
        466.0,
        85.0
      ],
      [
        467.0,
        85.0
      ],
      [
        468.0,
        85.0
      ],
      [
        469.0,
        85.0
      ],
      [
        470.0,
        85.0
      ],
      [
        471.0,
        86.0
      ],
      [
        472.0,
        86.0
      ],
      [
        473.0,
        86.0
      ],
      [
        474.0,
        86.0
      ],
      [
        475.0,
        86.0
      ],
      [
        476.0,
        86.0
      ],
      [
        477.0,
        86.0
      ],
      [
        478.0,
        86.0
      ],
      [
        479.0,
        86.0
      ],
      [
        480.0,
        86.0
      ],
      [
        481.0,
        86.0
      ],
      [
        482.0,
        86.0
      ],
      [
        483.0,
        86.0
      ],
      [
        484.0,
        86.0
      ],
      [
        485.0,
        86.0
      ],
      [
        486.0,
        86.0
      ],
      [
        487.0,
        86.0
      ],
      [
        488.0,
        86.0
      ],
      [
        489.0,
        85.0
      ],
      [
        490.0,
        85.0
      ],
      [
        491.0,
        85.0
      ],
      [
        492.0,
        85.0
      ],
      [
        493.0,
        85.0
      ],
      [
        494.0,
        85.0
      ],
      [
        495.0,
        85.0
      ],
      [
        496.0,
        85.0
      ],
      [
        497.0,
        85.0
      ],
      [
        498.0,
        85.0
      ],
      [
        499.0,
        85.0
      ],
      [
        500.0,
        85.0
      ],
      [
        501.0,
        85.0
      ],
      [
        502.0,
        85.0
      ],
      [
        503.0,
        85.0
      ],
      [
        504.0,
        85.0
      ],
      [
        505.0,
        85.0
      ],
      [
        506.0,
        85.0
      ],
      [
        507.0,
        85.0
      ],
      [
        508.0,
        84.0
      ],
      [
        509.0,
        84.0
      ]
    ]
  }
]